plover_clippy_2/__init__.py
plover_clippy_2/actions.py
plover_clippy_2/builtin.py
plover_clippy_2/config.py
plover_clippy_2/default.py
plover_clippy_2/sources.py
plover_clippy_2/state.py
plover_clippy_2/util.py
plover_clippy_2/algos/__init__.py
plover_clippy_2/algos/color.py
plover_clippy_2/algos/queue.py
plover_clippy_2/algos/retro.py
plover_clippy_2/distillations/__init__.py
plover_clippy_2/distillations/builtin.py
plover_clippy_2/distillations/repeat.py
plover_clippy_2/distillations/strokes.py
plover_clippy_2/extremity/__init__.py
plover_clippy_2/extremity/builtin.py
plover_clippy_2/extremity/start.py
plover_clippy_2/extremity/stop.py
plover_clippy_2/formatting/__init__.py
plover_clippy_2/formatting/builtin.py
plover_clippy_2/formatting/org.py
plover_clippy_2/formatting/retro.py
plover_clippy_2/formatting/color/__init__.py
plover_clippy_2/formatting/color/builtin.py
plover_clippy_2/formatting/color/palletes/__init__.py
plover_clippy_2/formatting/color/palletes/gruvbox.py
plover_clippy_2/hooks/__init__.py
plover_clippy_2/hooks/initialize.py
plover_clippy_2/hooks/start.py
plover_clippy_2/hooks/stop.py
plover_clippy_2/hooks/stroke.py
plover_clippy_2/hooks/translate.py
plover_clippy_2/translations/__init__.py
plover_clippy_2/translations/builtin.py
plover_clippy_2/translations/finger_spelling.py
plover_clippy_2/translations/org.py
plover_clippy_2/translations/retro.py
plover_clippy_2/translations/tk_fps.py
plover_clippy_2/translations/undo.py
plover_clippy_2-0.0.8.dist-info/LICENSE
plover_clippy_2-0.0.8.dist-info/METADATA
plover_clippy_2-0.0.8.dist-info/WHEEL
plover_clippy_2-0.0.8.dist-info/entry_points.txt
plover_clippy_2-0.0.8.dist-info/top_level.txt
plover_clippy_2-0.0.8.dist-info/zip-safe
plover_clippy_2-0.0.8.dist-info/RECORD
