Metadata-Version: 2.1
Name: plover-clippy-2
Version: 0.0.8
Summary: plover_clippy fork focused on extensibility and useability
Home-page: https://github.com/Josiah-tan/plover_clippy_2
Author: Josiah Tan
License: GNU General Public License v3 (GPLv3)
Keywords: plover plover_plugin plover_clippy
Classifier: Development Status :: 4 - Beta
Classifier: Environment :: Plugins
Classifier: Intended Audience :: End Users/Desktop
Classifier: License :: OSI Approved :: GNU General Public License v3 (GPLv3)
Classifier: Operating System :: OS Independent
Classifier: Programming Language :: Python :: 3
Classifier: Programming Language :: Python :: 3.7
License-File: LICENSE
Requires-Dist: plover (>=4.0.0.dev8)
